custom_repr/__init__.py
custom_repr/core.py
custom_repr-2.3.0.dist-info/LICENSE
custom_repr-2.3.0.dist-info/METADATA
custom_repr-2.3.0.dist-info/WHEEL
custom_repr-2.3.0.dist-info/top_level.txt
custom_repr-2.3.0.dist-info/RECORD
