Metadata-Version: 2.2
Name: custom-repr
Version: 2.3.0
Summary: A lightweight Python library to automatically generate clean __repr__ methods for all your user-declared classes.
Author-email: Pedro Fernandes da Silva <paca.fs@gmail.com>
License: MIT
Keywords: repr,string representation
Classifier: Programming Language :: Python :: 3
Classifier: License :: OSI Approved :: MIT License
Classifier: Operating System :: OS Independent
Requires-Python: >=3.7
License-File: LICENSE
Requires-Dist: rich>=10.0
